trustcall/__init__.py
trustcall/_base.py
trustcall/py.typed
trustcall1-0.0.39.dist-info/LICENSE
trustcall1-0.0.39.dist-info/METADATA
trustcall1-0.0.39.dist-info/WHEEL
trustcall1-0.0.39.dist-info/top_level.txt
trustcall1-0.0.39.dist-info/RECORD
