Metadata-Version: 2.2
Name: trustcall1
Version: 0.0.39
Summary: Tenacious & trustworthy tool calling built on LangGraph.
Author-email: William Fu-Hinthorn <13333726+hinthornw@users.noreply.github.com>
License: MIT
Requires-Python: <4.0,>=3.10
License-File: LICENSE
Requires-Dist: langgraph>=0.2.25
Requires-Dist: dydantic<1.0.0,>=0.0.8
Requires-Dist: jsonpatch<2.0,>=1.33
Requires-Dist: langgraph-prebuilt>=0.1.2
